ordlookup/__init__.py
ordlookup/oleaut32.py
ordlookup/ws2_32.py
pefile2/__init__.py
pefile2/pefile.py
pefile2/peutils.py
pefilev2/__init__.py
pefilev2/pefile.py
pefilev2/pefilev2.py
pefilev2/peutils.py
pefilev2-2.1.dist-info/DESCRIPTION.rst
pefilev2-2.1.dist-info/METADATA
pefilev2-2.1.dist-info/RECORD
pefilev2-2.1.dist-info/WHEEL
pefilev2-2.1.dist-info/metadata.json
pefilev2-2.1.dist-info/top_level.txt
peinfov2/__init__.py
peinfov2/pefile.py
peinfov2/peutils.py
