Metadata-Version: 2.0
Name: pefilev2
Version: 2.1
Summary: Parses a PE file and reports information on all properties of PE File
Home-page: UNKNOWN
Author: boddu
Author-email: b.manu199@icloud.com
License: UNKNOWN
Keywords: pefile,malicious,analysis
Platform: UNKNOWN
